openfigi_client/__init__.py
openfigi_client/_client.py
openfigi_client/_models.py
openfigi_client/exceptions.py
openfigi_client-0.4.2.dist-info/METADATA
openfigi_client-0.4.2.dist-info/WHEEL
openfigi_client-0.4.2.dist-info/licenses/LICENSE
openfigi_client-0.4.2.dist-info/RECORD
