Metadata-Version: 2.4
Name: openfigi-client
Version: 0.4.2
Summary: Python client for the OpenFIGI API.
Author-email: ljnsn <info@ljnsn.com>
License: MIT License
License-File: LICENSE
Keywords: api,bloomberg,figi,openfigi,python
Classifier: Development Status :: 5 - Production/Stable
Classifier: Intended Audience :: Developers
Classifier: License :: OSI Approved :: MIT License
Classifier: Operating System :: OS Independent
Classifier: Programming Language :: Python
Classifier: Programming Language :: Python :: 3 :: Only
Classifier: Programming Language :: Python :: 3.10
Classifier: Programming Language :: Python :: 3.11
Classifier: Programming Language :: Python :: 3.12
Classifier: Programming Language :: Python :: 3.13
Classifier: Topic :: Software Development :: Libraries
Classifier: Topic :: Software Development :: Libraries :: Python Modules
Classifier: Typing :: Typed
Requires-Python: >=3.10
Requires-Dist: httpx>=0.27.2
Requires-Dist: msgspec>=0.18.6
